os_schedules/__init__.py
myos-0.0.1.dist-info/METADATA
myos-0.0.1.dist-info/WHEEL
myos-0.0.1.dist-info/top_level.txt
myos-0.0.1.dist-info/RECORD
