Metadata-Version: 2.4
Name: myos
Version: 0.0.1
Summary: OS Practicals: Interactive & Static versions with Helper Tips
Author-email: Hafiz_M <hafizmujawar786@gmail.com>
Project-URL: Homepage, https://pypi.org/user/Hafiz_M/
Classifier: Programming Language :: Python :: 3
Classifier: License :: OSI Approved :: MIT License
Classifier: Operating System :: OS Independent
Requires-Python: >=3.7
